{
    "title" : "Black Widow",
    "image" : "https://www.google.com/url?sa=i&url=https%3A%2F%2Feconomictimes.indiatimes.com%2Fmagazines%2Fpanache%2Fdisney-wants-to-release-scarlett-johansson-starrer-black-widow-in-theatres%2Farticleshow%2F80880651.cms&psig=AOvVaw3Ru1Dj4cppErmyYU4Rn9j5&ust=1634724784272000&source=images&cd=vfe&ved=0CAsQjRxqFwoTCIDw4eae1vMCFQAAAAAdAAAAABAK",
    "description" :"Black Widow is a deadly one-woman fighting force. An expert in many forms of martial arts.",
    "power" : ["Strength","Speed","Endurance","Avenger"],
    "widget_color" :"black",
    "text_color" :"white", 
    "dialogue":"The Best Part Of My Life Was Fake And None Of You Told Me",
    "author" : "Mohak Khetan"
}
